highlighting_atoms/__init__.py
highlighting_atoms/highlighting_atoms.py
highlighting_atoms-0.3.dist-info/LICENSE
highlighting_atoms-0.3.dist-info/METADATA
highlighting_atoms-0.3.dist-info/WHEEL
highlighting_atoms-0.3.dist-info/top_level.txt
highlighting_atoms-0.3.dist-info/RECORD
