Metadata-Version: 2.1
Name: highlighting_atoms
Version: 0.3
Summary: Highlighting atoms function
Home-page: https://github.com/phi-grib/highlighting_atoms
Download-URL: https://github.com/phi-grib/highlighting_atoms
Author: Pablo Rodríguez Belenguer
Author-email: parodbe@gmail.com
License: GNU
License-File: LICENSE
